krovak05/__init__.py
krovak05/krovak05.py
krovak05/test_krova05.py
krovak05/difference_tables/__init__.py
krovak05/difference_tables/table_yx_3_v1005.csv
krovak05/difference_tables/table_yx_3_v1202.csv
krovak05/difference_tables/table_yx_3_v1710.csv
krovak05/kvazigeoids/CR-2005_v1005.csv
krovak05/kvazigeoids/__init__.py
krovak05-0.0.9.dist-info/LICENSE
krovak05-0.0.9.dist-info/METADATA
krovak05-0.0.9.dist-info/WHEEL
krovak05-0.0.9.dist-info/top_level.txt
krovak05-0.0.9.dist-info/RECORD
