Metadata-Version: 2.1
Name: krovak05
Version: 0.0.9
Summary: geodetic package for transformation ETRS coordinates to S-JTSK
Home-page: https://github.com/SteveeH/krovak05
Author: SteveH
Author-email: steveeh07@gmail.com
License: UNKNOWN
Platform: UNKNOWN
Classifier: Programming Language :: Python :: 3
Classifier: License :: OSI Approved :: GNU General Public License v3 (GPLv3)
Classifier: Operating System :: OS Independent
License-File: LICENSE
Provides-Extra: dev
Requires-Dist: pytest (>=7.0) ; extra == 'dev'
